coconut/__init__.py
coconut/nut/__init__.py
coconut/nut/for_torch.py
coconut_nut-0.1.4.dist-info/METADATA
coconut_nut-0.1.4.dist-info/WHEEL
coconut_nut-0.1.4.dist-info/licenses/LICENSE
coconut_nut-0.1.4.dist-info/RECORD
